COPYING.gpl3
MANIFEST.in
README.rst
setup.py
prometheus_smart_exporter/__init__.py
prometheus_smart_exporter/__main__.py
prometheus_smart_exporter/attrmeta.py
prometheus_smart_exporter/devicedb.py
prometheus_smart_exporter.egg-info/PKG-INFO
prometheus_smart_exporter.egg-info/SOURCES.txt
prometheus_smart_exporter.egg-info/dependency_links.txt
prometheus_smart_exporter.egg-info/entry_points.txt
prometheus_smart_exporter.egg-info/requires.txt
prometheus_smart_exporter.egg-info/top_level.txt
prometheus_smart_exporter/data/attrmap.json
smart_exporter_helper/__init__.py
smart_exporter_helper/__main__.py