Metadata-Version: 1.1
Name: prometheus-smart-exporter
Version: 0.2.2
Summary: S.M.A.R.T. exporter for Prometheus
Home-page: https://github.com/cloudandheat/prometheus_smart_exporter
Author: Jonas Wielicki
Author-email: jonas.wielicki@cloudandheat.com
License: UNKNOWN
Keywords: prometheus smart monitoring hdd ssd
Platform: UNKNOWN
Classifier: Development Status :: 4 - Beta
Classifier: Intended Audience :: System Administrators
Classifier: Operating System :: Unix
Classifier: Operating System :: POSIX :: Linux
Classifier: License :: OSI Approved :: GNU General Public License v3 or later (GPLv3+)
Classifier: Programming Language :: Python :: 3
Classifier: Topic :: System :: Monitoring
